streamlit_clickable_list/__init__.py
streamlit_clickable_list/frontend/build/asset-manifest.json
streamlit_clickable_list/frontend/build/bootstrap.min.css
streamlit_clickable_list/frontend/build/index.html
streamlit_clickable_list/frontend/build/static/js/main.f2ac4e10.js
streamlit_clickable_list/frontend/build/static/js/main.f2ac4e10.js.LICENSE.txt
streamlit_clickable_list/frontend/build/static/js/main.f2ac4e10.js.map
streamlit_clickable_list/frontend/node_modules/flatted/python/flatted.py
streamlit_clickable_list/frontend/node_modules/flatted/python/test.py
streamlit_clickable_list-0.1.4.dist-info/LICENSE
streamlit_clickable_list-0.1.4.dist-info/METADATA
streamlit_clickable_list-0.1.4.dist-info/WHEEL
streamlit_clickable_list-0.1.4.dist-info/top_level.txt
streamlit_clickable_list-0.1.4.dist-info/RECORD
