Metadata-Version: 2.2
Name: streamlit-clickable-list
Version: 0.1.4
Summary: A simple clickable list component for streamlit
Author: mu-777
Project-URL: Repository, https://github.com/mu-777/streamlit-clickable-list
Project-URL: Demo, https://clickable-list.streamlit.app/
Keywords: streamlit,component,clickable,list,text
Requires-Python: >=3.9
License-File: LICENSE
Requires-Dist: streamlit>=0.63
